{
  "id": "exam_topic:abo-codominance",
  "type": "exam_topic",
  "title": "ABO blood typing and codominance — how does it work?",
  "slug": "abo-codominance",
  "aliases": [],
  "tags": [
    "exam-3",
    "chapter-10",
    "codominance",
    "blood-typing"
  ],
  "status": "active",
  "wiki_path": "wiki/exam-topics/abo-codominance.md",
  "summary": "",
  "source_refs": [],
  "confidence": 1.0,
  "provenance": {
    "ingested_from": [
      "wiki/exam-topics/abo-codominance.md"
    ],
    "method": "parser",
    "extractor_version": "0.1.0"
  },
  "version": 1,
  "created": "2026-04-29",
  "updated": "2026-04-29",
  "chapters": [
    10
  ]
}
